get_cover_art/__init__.py
get_cover_art/__main__.py
get_cover_art/apple_downloader.py
get_cover_art/base_ogg.py
get_cover_art/cover_finder.py
get_cover_art/deromanizer.py
get_cover_art/meta_audio.py
get_cover_art/meta_flac.py
get_cover_art/meta_mp3.py
get_cover_art/meta_mp4.py
get_cover_art/meta_opus.py
get_cover_art/meta_vorbis.py
get_cover_art/normalizer.py
get_cover_art/meta/__init__.py
get_cover_art/meta/base_id3.py
get_cover_art/meta/base_ogg.py
get_cover_art/meta/meta_audio.py
get_cover_art/meta/meta_dsf.py
get_cover_art/meta/meta_flac.py
get_cover_art/meta/meta_mp3.py
get_cover_art/meta/meta_mp4.py
get_cover_art/meta/meta_opus.py
get_cover_art/meta/meta_vorbis.py
get_cover_art/meta/meta_wav.py
get_cover_art-1.8.3.dist-info/LICENSE
get_cover_art-1.8.3.dist-info/METADATA
get_cover_art-1.8.3.dist-info/WHEEL
get_cover_art-1.8.3.dist-info/entry_points.txt
get_cover_art-1.8.3.dist-info/top_level.txt
get_cover_art-1.8.3.dist-info/RECORD
