Metadata-Version: 2.1
Name: get-cover-art
Version: 1.8.3
Summary: Batch cover art downloader and embedder for audio files
Home-page: https://github.com/regosen/get_cover_art
Author: Rego Sen
Author-email: regosen@gmail.com
License: MIT
Keywords: cover album art artwork embed itunes apple music mp3 id3 m4a m4b mp4 aac xmp flac dsf ogg vorbis opus wav songs
Platform: UNKNOWN
Classifier: Development Status :: 4 - Beta
Classifier: Environment :: Console
Classifier: Intended Audience :: End Users/Desktop
Classifier: License :: OSI Approved :: MIT License
Classifier: Operating System :: OS Independent
Classifier: Programming Language :: Python
Classifier: Programming Language :: Python :: 3
Classifier: Topic :: Internet
Classifier: Topic :: Multimedia :: Graphics
Classifier: Topic :: Multimedia :: Sound/Audio
Requires-Python: >=3.5
License-File: LICENSE
Requires-Dist: mutagen
